Ptt_Crawlers/__init__.py
Ptt_Crawlers/ptt_search.py
Async_Ptt_Crawler-1.3.dist-info/METADATA
Async_Ptt_Crawler-1.3.dist-info/WHEEL
Async_Ptt_Crawler-1.3.dist-info/top_level.txt
Async_Ptt_Crawler-1.3.dist-info/RECORD
